MANIFEST.in
README.md
setup.py
bin/cluf
cluster_func/__init__.py
cluster_func/_cf.py
cluster_func/arg_parser.py
cluster_func/arguments.py
cluster_func/exceptions.py
cluster_func/rc_params.py
cluster_func/utils.py
cluster_func.egg-info/PKG-INFO
cluster_func.egg-info/SOURCES.txt
cluster_func.egg-info/dependency_links.txt
cluster_func.egg-info/requires.txt
cluster_func.egg-info/top_level.txt