Metadata-Version: 1.1
Name: cluster-func
Version: 0.0.6
Summary: Run a function many times on many processes / machines
Home-page: https://github.com/enewe101/cluster-func
Author: Edward Newell
Author-email: edward.newell@gmail.com
License: MIT
Keywords: threading multiprocessing schedule scheduling batch process processing queue queueing cluster qsub pbs
Platform: UNKNOWN
Classifier: Development Status :: 3 - Alpha
Classifier: Intended Audience :: Developers
Classifier: Topic :: Software Development :: Build Tools
Classifier: License :: OSI Approved :: MIT License
Classifier: Programming Language :: Python :: 2.7
